benchmarking/dataset/cora/prepare.py
benchmarking/dataset/dataset_builder/__init__.py
benchmarking/dataset/dataset_builder/dataset_builder.py
benchmarking/dataset/dataset_builder/dataset_builder_modified.py
benchmarking/dataset/dataset_builder/dataset_builder_np.py
benchmarking/dataset/dataset_builder/dataset_builder_static.py
benchmarking/dataset/preprocessing/preprocess_temporal_data.py
benchmarking/dynamic-temporal-tgcn/pygt/model.py
benchmarking/dynamic-temporal-tgcn/pygt/train.py
benchmarking/dynamic-temporal-tgcn/pygt/utils.py
benchmarking/dynamic-temporal-tgcn/seastar/model.py
benchmarking/dynamic-temporal-tgcn/seastar/train.py
benchmarking/dynamic-temporal-tgcn/seastar/utils.py
benchmarking/gat/seastar/model.py
benchmarking/gat/seastar/train.py
benchmarking/gat/seastar/utils.py
benchmarking/gcn/seastar/model.py
benchmarking/gcn/seastar/train.py
benchmarking/gcn/seastar/utils.py
benchmarking/results/result_generator_static.py
benchmarking/static-temporal-tgcn/pygt/model.py
benchmarking/static-temporal-tgcn/pygt/train.py
benchmarking/static-temporal-tgcn/pygt/utils.py
benchmarking/static-temporal-tgcn/seastar/model.py
benchmarking/static-temporal-tgcn/seastar/train.py
benchmarking/static-temporal-tgcn/seastar/utils.py
docs/conf.py
stgraph/__init__.py
stgraph/benchmark_tools/__init__.py
stgraph/benchmark_tools/table.py
stgraph/compiler/__init__.py
stgraph/compiler/autodiff.py
stgraph/compiler/execution_unit.py
stgraph/compiler/executor.py
stgraph/compiler/node.py
stgraph/compiler/program.py
stgraph/compiler/registry.py
stgraph/compiler/schema.py
stgraph/compiler/stgraph.py
stgraph/compiler/utils.py
stgraph/compiler/backend/__init__.py
stgraph/compiler/backend/callback.py
stgraph/compiler/backend/kernel_wrapper.py
stgraph/compiler/backend/mxnet/__init__.py
stgraph/compiler/backend/pytorch/__init__.py
stgraph/compiler/backend/pytorch/torch_callback.py
stgraph/compiler/backend/pytorch/torch_kernel_wrapper.py
stgraph/compiler/backend/tensorflow/__init__.py
stgraph-1.0.0.dist-info/LICENSE
stgraph-1.0.0.dist-info/METADATA
stgraph-1.0.0.dist-info/WHEEL
stgraph-1.0.0.dist-info/top_level.txt
stgraph-1.0.0.dist-info/RECORD
