Metadata-Version: 2.1
Name: stgraph
Version: 1.0.0
Summary: 🌟 Vertex Centric approach for building GNN/TGNNs
Author-email: Joel Mathew Cherian <joelmathewcherian@gmail.com>, Nithin Puthalath Manoj <nithinp.manoj@gmail.com>
License: MIT License
Project-URL: Homepage, https://github.com/bfGraph/STGraph
Keywords: GNN,TGNN,GPU Programming
Classifier: Programming Language :: Python :: 3
Classifier: License :: OSI Approved :: MIT License
Classifier: Operating System :: POSIX :: Linux
Requires-Python: >=3.8
License-File: LICENSE
Requires-Dist: Jinja2 >=2
Requires-Dist: pynvrtc >=9.2
Requires-Dist: pydot
Requires-Dist: networkx >=3.1
Requires-Dist: sympy >=1.11.1
Requires-Dist: cuda-python >=12.1.0
Requires-Dist: numpy >=1.23.4
Requires-Dist: pandas >=1.3.5
Requires-Dist: prettytable >=3.7.0
Requires-Dist: pybind11 >=2.10.4
Requires-Dist: rich >=13.3.5
Requires-Dist: snoop >=0.4.2
Requires-Dist: termcolor >=2.3.0
Provides-Extra: dev
Requires-Dist: black ; extra == 'dev'
Requires-Dist: pytest ; extra == 'dev'
Requires-Dist: tqdm >=4.64.1 ; extra == 'dev'
Requires-Dist: build >=0.10.0 ; extra == 'dev'
Requires-Dist: gdown >=4.6.6 ; extra == 'dev'
Requires-Dist: pynvml >=11.5.0 ; extra == 'dev'
Requires-Dist: sphinx-rtd-theme >=1.2.0 ; extra == 'dev'
